bnq_py_core/__init__.py
bnq_py_core/cos_connect.py
bnq_py_core/logger_record.py
bnq_py_core/nacos_conf.py
bnq_py_core/nacos_connect.py
bnq_py_core/read_conf_from_ini.py
bnq_py_core/singleton.py
bnq_py_core/util/__init__.py
bnq_py_core/util/time_zone.py
bnq_py_core/utils/__init__.py
bnq_py_core/utils/time_zone.py
common_tools_ai_bnq-0.2.3.dist-info/METADATA
common_tools_ai_bnq-0.2.3.dist-info/WHEEL
common_tools_ai_bnq-0.2.3.dist-info/top_level.txt
common_tools_ai_bnq-0.2.3.dist-info/RECORD
