Metadata-Version: 2.1
Name: common-tools-ai-bnq
Version: 0.2.3
Summary: Common tools of AI module for BNQ
Home-page: UNKNOWN
Author: BNQ
License: UNKNOWN
Platform: UNKNOWN
Requires-Dist: structlog (==23.1.0)
Requires-Dist: concurrent-log-handler (==0.9.25)
Requires-Dist: nacos-sdk-python (==0.1.12)
Requires-Dist: PyYAML (==6.0.1)
Requires-Dist: cos-python-sdk-v5 (==1.9.28)
Requires-Dist: termcolor (==2.4.0)
Requires-Dist: pytz (==2024.1)
